{"timestamp":1571186448152,"grid_size":12,"polygons":[{"bounds":[6,6,6,6],"triangle_points":[0,4,1,6,3,1,1,6,6,6,3,1,6,6,6,3,3,1,6,3,4,0,3,1]},{"bounds":[0,8,7,4],"triangle_points":[0,0,0,4,5,2,5,2,0,4,6,2,0,4,7,4,6,2]},{"bounds":[6,4,3,6],"triangle_points":[1,0,0,0,3,3,0,0,0,6,3,3]},{"bounds":[3,4,3,6],"triangle_points":[2,6,3,6,0,2,3,6,3,0,0,2,3,0,2,0,0,2]},{"bounds":[0,6,5,4],"triangle_points":[0,2,5,4,0,1,5,4,3,0,0,1]},{"bounds":[7,4,5,3],"triangle_points":[5,0,0,0,3,2,0,0,2,3,3,2]},{"bounds":[10,4,2,5],"triangle_points":[2,0,0,2,2,5]},{"bounds":[7,0,5,4],"triangle_points":[0,4,5,4,1,0,5,4,5,0,1,0]},{"bounds":[0,2,3,5],"triangle_points":[0,0,0,5,3,4]},{"bounds":[1,0,7,4],"triangle_points":[6,4,7,0,5,4,5,4,7,0,4,4,7,0,0,0,4,4]},{"bounds":[0,0,5,6],"triangle_points":[1,0,0,0,5,4,0,0,0,2,5,4,0,2,3,6,5,4]}]}